adwords_client/__init__.py
adwords_client/client.py
adwords_client/client_operations.py
adwords_client/sqlite.py
adwords_client/utils.py
adwords_client/__pycache__/__init__.cpython-36.pyc
adwords_client/__pycache__/client.cpython-36.pyc
adwords_client/__pycache__/client_operations.cpython-36.pyc
adwords_client/__pycache__/sqlite.cpython-36.pyc
adwords_client/__pycache__/utils.cpython-36.pyc
adwords_client/adwordsapi/__init__.py
adwords_client/adwordsapi/batch_job_service.py
adwords_client/adwordsapi/common.py
adwords_client/adwordsapi/label_service.py
adwords_client/adwordsapi/operations.py
adwords_client/adwordsapi/report_downloader.py
adwords_client/adwordsapi/sync_job_service.py
adwords_client/adwordsapi/__pycache__/__init__.cpython-36.pyc
adwords_client/adwordsapi/__pycache__/batch_job_service.cpython-36.pyc
adwords_client/adwordsapi/__pycache__/common.cpython-36.pyc
adwords_client/adwordsapi/__pycache__/label_service.cpython-36.pyc
adwords_client/adwordsapi/__pycache__/operations.cpython-36.pyc
adwords_client/adwordsapi/__pycache__/report_downloader.cpython-36.pyc
adwords_client/adwordsapi/__pycache__/sync_job_service.cpython-36.pyc
adwords_client/mappers/__init__.py
adwords_client/mappers/redshift.py
adwords_client/mappers/__pycache__/__init__.cpython-36.pyc
adwords_client/mappers/__pycache__/redshift.cpython-36.pyc
adwords_client-17.7.dist-info/DESCRIPTION.rst
adwords_client-17.7.dist-info/METADATA
adwords_client-17.7.dist-info/RECORD
adwords_client-17.7.dist-info/WHEEL
adwords_client-17.7.dist-info/metadata.json
adwords_client-17.7.dist-info/top_level.txt
