Metadata-Version: 2.0
Name: adwords-client
Version: 17.7
Summary: AdWords Client with read/write support
Home-page: https://github.com/getninjas/adwords-client
Author: Samuel Martins Barbosa Neto et al.
Author-email: sam@getninjas.com.br
License: APACHE
Platform: UNKNOWN
Classifier: Development Status :: 5 - Production/Stable
Classifier: Environment :: Web Environment
Classifier: Intended Audience :: Developers
Classifier: License :: OSI Approved :: Apache Software License
Classifier: Operating System :: OS Independent
Classifier: Natural Language :: English
Classifier: Programming Language :: Python :: 3 :: Only
Classifier: Programming Language :: Python :: 3
Classifier: Programming Language :: Python :: 3.5
Classifier: Programming Language :: Python :: 3.6
Classifier: Topic :: Internet
Classifier: Topic :: Software Development :: Libraries :: Python Modules
Requires-Python: ~=3.5
Requires-Dist: PyYAML (>=3.12)
Requires-Dist: SQLAlchemy (>=1.1.9)
Requires-Dist: boto3 (>=1.4.4)
Requires-Dist: google-api-python-client (>=1.6.2)
Requires-Dist: googleads (>=5.3.0)
Requires-Dist: oauth2client (>=4.0.0)
Requires-Dist: pandas (>=0.19.2)
Requires-Dist: psycopg2 (>=2.7.1)
Requires-Dist: python-dateutil (>=2.6.0)
Requires-Dist: pytz (>=2017.2)
Requires-Dist: requests (>=2.13.0)
Requires-Dist: sqlalchemy-redshift (>=0.5.0)
Requires-Dist: suds-jurko (>=0.6)
